[
   { "FirstName" : "Jonas", "LastName" : "Martin",   "Email" : "jonas@gmail.com", "PhoneNo": "432232233", "Status": "Active"},
   { "FirstName" : "John", "LastName" : "Maxwell",   "Email" : "john@gmail.com", "PhoneNo": "424232233", "Status": "Active"},
   { "FirstName" : "Maximillan", "LastName" : "Pointing",   "Email" : "maximillan@gmail.com", "PhoneNo": "5454545454", "Status": "Active"},
   { "FirstName" : "Sara", "LastName" : "Flemming",   "Email" : "sara@gmail.com", "PhoneNo": "554445454", "Status": "Active"},
   { "FirstName" : "Mike", "LastName" : "Hussey",   "Email" : "mike@gmail.com", "PhoneNo": "545454545", "Status": "Active"},
   { "FirstName" : "Glen", "LastName" : "Bond",   "Email" : "glen@gmail.com", "PhoneNo": "434343434", "Status": "Active"},
   { "FirstName" : "Ricky", "LastName" : "Pointing",   "Email" : "ricky@gmail.com", "PhoneNo": "6456456564", "Status": "Active"},
   { "FirstName" : "Adam", "LastName" : "Gilchrist",   "Email" : "adam@gmail.com", "PhoneNo": "43423333", "Status": "Active"}               
]